adversary_mcp_server/__init__.py
adversary_mcp_server/config.py
adversary_mcp_server/config_manager.py
adversary_mcp_server/container.py
adversary_mcp_server/credentials.py
adversary_mcp_server/logger.py
adversary_mcp_server/sync_main.py
adversary_mcp_server/application/__init__.py
adversary_mcp_server/application/bootstrap_clean.py
adversary_mcp_server/application/mcp_server.py
adversary_mcp_server/application/adapters/__init__.py
adversary_mcp_server/application/adapters/input_models.py
adversary_mcp_server/application/adapters/llm_adapter.py
adversary_mcp_server/application/adapters/llm_validation_adapter.py
adversary_mcp_server/application/adapters/mock_semgrep_adapter.py
adversary_mcp_server/application/adapters/semgrep_adapter.py
adversary_mcp_server/application/adapters/session_aware_llm_adapter.py
adversary_mcp_server/application/adapters/telemetry_adapter.py
adversary_mcp_server/application/cli/__init__.py
adversary_mcp_server/application/cli/clean_cli.py
adversary_mcp_server/application/formatters/__init__.py
adversary_mcp_server/application/formatters/domain_result_formatter.py
adversary_mcp_server/application/services/__init__.py
adversary_mcp_server/application/services/false_positive_service.py
adversary_mcp_server/application/services/scan_application_service.py
adversary_mcp_server/application/services/scan_persistence_service.py
adversary_mcp_server/batch/__init__.py
adversary_mcp_server/batch/batch_processor.py
adversary_mcp_server/batch/token_estimator.py
adversary_mcp_server/batch/types.py
adversary_mcp_server/benchmarks/__init__.py
adversary_mcp_server/benchmarks/benchmark_runner.py
adversary_mcp_server/benchmarks/results.py
adversary_mcp_server/benchmarks/test_scenarios.py
adversary_mcp_server/cache/__init__.py
adversary_mcp_server/cache/cache_manager.py
adversary_mcp_server/cache/config_tracker.py
adversary_mcp_server/cache/content_hasher.py
adversary_mcp_server/cache/serializable_types.py
adversary_mcp_server/cache/types.py
adversary_mcp_server-1.11.1.dist-info/METADATA
adversary_mcp_server-1.11.1.dist-info/WHEEL
adversary_mcp_server-1.11.1.dist-info/entry_points.txt
adversary_mcp_server-1.11.1.dist-info/licenses/LICENSE
adversary_mcp_server-1.11.1.dist-info/RECORD
