Metadata-Version: 2.4
Name: adversary-mcp-server
Version: 1.11.1
Summary: MCP server for security vulnerability scanning and detection
Project-URL: Homepage, https://github.com/brettbergin/adversary-mcp-server
Project-URL: Documentation, https://github.com/brettbergin/adversary-mcp-server#readme
Project-URL: Repository, https://github.com/brettbergin/adversary-mcp-server.git
Project-URL: Issues, https://github.com/brettbergin/adversary-mcp-server/issues
Author-email: Brett Bergin <brettberginbc@yahoo.com>
License: MIT
License-File: LICENSE
Keywords: mcp,scanner,security,static-analysis,vulnerability
Classifier: Development Status :: 4 - Beta
Classifier: Intended Audience :: Developers
Classifier: License :: OSI Approved :: MIT License
Classifier: Operating System :: OS Independent
Classifier: Programming Language :: Python :: 3
Classifier: Programming Language :: Python :: 3.11
Classifier: Programming Language :: Python :: 3.12
Classifier: Topic :: Security
Classifier: Topic :: Software Development :: Libraries :: Python Modules
Classifier: Topic :: Software Development :: Quality Assurance
Requires-Python: <3.14,>=3.10
Requires-Dist: aiohttp>=3.9.0
Requires-Dist: anthropic>=0.8.0
Requires-Dist: click>=8.0.0
Requires-Dist: cryptography>=3.4.8
Requires-Dist: jinja2==3.1.6
Requires-Dist: keyring>=24.0.0
Requires-Dist: mcp>=1.0.0
Requires-Dist: openai>=1.0.0
Requires-Dist: pathspec>=0.11.0
Requires-Dist: psutil>=5.9.0
Requires-Dist: pydantic>=2.0.0
Requires-Dist: pyyaml>=6.0.0
Requires-Dist: questionary>=2.0.0
Requires-Dist: requests>=2.28.0
Requires-Dist: rich>=13.0.0
Requires-Dist: semgrep>=1.0.0
Requires-Dist: sqlalchemy>=2.0.0
Requires-Dist: truststore>=0.8.0
Requires-Dist: typing-extensions>=4.0.0
Provides-Extra: dev
Requires-Dist: black>=23.0.0; extra == 'dev'
Requires-Dist: freezegun>=1.2.0; extra == 'dev'
Requires-Dist: isort>=5.0.0; extra == 'dev'
Requires-Dist: mypy>=1.0.0; extra == 'dev'
Requires-Dist: pre-commit>=3.0.0; extra == 'dev'
Requires-Dist: pytest-asyncio>=0.21.0; extra == 'dev'
Requires-Dist: pytest-benchmark>=4.0.0; extra == 'dev'
Requires-Dist: pytest-cov>=4.0.0; extra == 'dev'
Requires-Dist: pytest-mock>=3.10.0; extra == 'dev'
Requires-Dist: pytest>=7.0.0; extra == 'dev'
Requires-Dist: responses>=0.24.0; extra == 'dev'
Requires-Dist: ruff>=0.1.0; extra == 'dev'
